PS2Interface/seven_segment_led/bcd_to_seven_seg.v
module bcd_to_seven_seg (input [3:0] val_in, output logic [6:0] led_out);

    // val_in is in BCD format, 4 bits used to describe 0-9 in decimal

    // LED out LSB is G, MSB is A

    // SOP product terms for each decimal value
    wire bcd0, bcd1, bcd2, bcd3, bcdd4, bcd5, bcd6, bcd7, bcd8, bcd9;

    assign bcd0 = ~val_in[3] & ~val_in[2] & ~val_in[1] & ~val_in[0];
    assign bcd1 = ~val_in[3] & ~val_in[2] & ~val_in[1] & val_in[0];
    assign bcd2 = ~val_in[3] & ~val_in[2] & val_in[1] & ~val_in[0];
    assign bcd3 = ~val_in[3] & ~val_in[2] & val_in[1] & val_in[0];
    assign bcd4 = ~val_in[3] & val_in[2] & ~val_in[1] & ~val_in[0];
    assign bcd5 = ~val_in[3] & val_in[2] & ~val_in[1] & val_in[0];
    assign bcd6 = ~val_in[3] & val_in[2] & val_in[1] & ~val_in[0];
    assign bcd7 = ~val_in[3] & val_in[2] & val_in[1] & val_in[0];
    assign bcd8 = val_in[3] & ~val_in[2] & ~val_in[1] & ~val_in[0];
    assign bcd9 = val_in[3] & ~val_in[2] & ~val_in[1] & val_in[0];
    
    // A
    assign led_out[6] = bcd1 & bcd4;

    // B
    assign led_out[5] = bcd5 & bcd6;

    // C
    assign led_out[4] = bcd2;

    // D
    assign led_out[3] = bcd1 & bcd4 & bcd7;

    // E
    assign led_out[2] = bcd1 & bcd3 & bcd4 & bcd7 & bcd9;

    // F
    assign led_out[1] = bcd1 & bcd2 & bcd3 & bcd5 & bcd7;

    // G
    assign led_out[0] = bcd0 & bcd1 & bcd7;

endmodule

PS2Interface/seven_segment_led/bin2bcd.v
module bin2bcd(
   input [13:0] bin,
   output reg [15:0] bcd
   );
   
    integer i;
        
    always @(bin) begin
        bcd=0;	 	
        for (i=0;i<14;i=i+1) begin					//Iterate once for each bit in input number
            if (bcd[3:0] >= 5) 
                bcd[3:0] = bcd[3:0] + 3;		//If any BCD digit is >= 5, add three
            if (bcd[7:4] >= 5) 
                bcd[7:4] = bcd[7:4] + 3;
            if (bcd[11:8] >= 5) 
                bcd[11:8] = bcd[11:8] + 3;
            if (bcd[15:12] >= 5) 
                bcd[15:12] = bcd[15:12] + 3;
            bcd = { bcd[14:0], bin[13-i] };				//Shift one bit, and shift in proper bit from input 
        end
    end
endmodule

PS2Interface/seven_segment_led/seven_segment.v
module seven_segment(input clk_in, 
                     input rst_in, 
                     input [31:0] val_in, // in binary format
                     output [7:0] cat_out, // LSB is G, MSB - 1 is A
                     output [3:0] an_out);

    // take a binary 32 bit value, convert to BCD, switch between 4 bits of BCD, then convert to cathode values and anode

    reg [3:0] segment_state = 4'b0001;
    reg [31:0] segment_counter = 32'd0;
    reg [3:0] routed_vals;
    wire [6:0] led_out;

    wire [15:0] bcd;
    bin2bcd bintobcd(val_in[13:0], bcd);
    
    bcd_to_seven_seg my_converter (.val_in(routed_vals),.led_out(led_out));
    assign cat_out = {1'b1, led_out}; // make decimal the 1
    assign an_out = ~segment_state;
    
//    always @(segment_state) begin
//        case(segment_state)
//            4'b0001:   routed_vals = bcd[3:0];
//            4'b0010:   routed_vals = bcd[7:4];
//            4'b0100:   routed_vals = bcd[11:8];
//            4'b1000:   routed_vals = bcd[15:12];
//            default:   routed_vals = bcd[3:0];
//        endcase
//    end
    
    always @(posedge clk_in) begin
        if (rst_in)begin
            segment_state <= 4'b0001;
            segment_counter <= 32'b0;
        end else begin
            segment_state <= {segment_state[2:0],segment_state[3]};
//            if (segment_counter < 32'd100000) begin
//                segment_counter <= 32'd0;
//                segment_state <= {segment_state[2:0],segment_state[3]};
//            end else begin
//                segment_counter <= segment_counter + 1;
//            end
        end
        
        case(segment_state)
            4'b0001:   routed_vals = bcd[3:0];
            4'b0010:   routed_vals = bcd[7:4];
            4'b0100:   routed_vals = bcd[11:8];
            4'b1000:   routed_vals = bcd[15:12];
            default:   routed_vals = bcd[3:0];
        endcase
    end
        
endmodule

PS2Interface/custom_tb.v
`timescale 100 ps / 10 ps
module custom_tb;
    wire [31:0] in0, in1, in2, in3, in4, in5, in6, in7;

    reg clock = 0;

    wire [31:0] temp1, temp2, temp3, temp4, temp5, temp6;
    wire t1, t2, t3, t4, t5, t6, t7;
	
	integer i;

    integer m0;
    integer m1;
    integer m2;
    integer m3;
    integer m4;
    integer m5;


    assign in0 = m0;
    assign in1 = m1;
    assign in2 = m2;

    ///////////////////
    //
    // iverilog -o f_custom_tb.vvp -s custom_tb custom_tb.v
    //
    // iverilog -o f_custom_tb.vvp -s custom_tb custom_tb.v seven_segment_led/bcd_to_seven_seg.v seven_segment_led/bin2bcd.v seven_segment_led/seven_segment.v
    //
    ///////////////////
    
    // VGAController vga(clock, 1'b0, 1'b1, 1'b1, 1'b1, 1'b1, t1, t2, t3, temp1[3:0], temp2[3:0], temp3[3:0], t4, t5, t6, t7);
    
//    VGAController(input clk, 			// 100 MHz System Clock
//	input reset, 		// Reset Signal
//	input move_up,
//	input move_down,
//	input move_right,
//	input move_left,
//	output debug1,
//	output hSync, 		// H Sync Signal
//	output vSync, 		// Veritcal Sync Signal
//	output[3:0] VGA_R,  // Red Signal Bits
//	output[3:0] VGA_G,  // Green Signal Bits
//	output[3:0] VGA_B,  // Blue Signal Bits
//	inout ps2_clk,
//	inout ps2_data);
    localparam FILES_PATH = "C:/Users/fj32/OneDrive - Duke University/Documents/guitar_hero/GuitarHero/PS2Interface/";
    localparam MAX_NOTES_ON_SCREEN = 21;
    reg[3:0] NOTES[0:MAX_NOTES_ON_SCREEN - 1];
    wire [MAX_NOTES_ON_SCREEN-1:0] felix;
    assign felix = m0[MAX_NOTES_ON_SCREEN-1:0];
    assign hi =|felix;
    reg[3:0] maybe;

    assign temp2 = m0;

    // bin2bcd ftest(temp2[13:0], temp1[15:0]);

    seven_segment segtest(clock, 1'b0, temp2, temp1[7:0], temp3[3:0]);
    bcd_to_seven_seg fsklefj(temp2[3:0], temp4[6:0]);

    initial begin
        $dumpfile("gtkwave.vcd");
		// Module to capture and what level, 0 means all wires
		$dumpvars(0, custom_tb);
        for(i = 0; i < 16; i = i + 1) begin
            m0 = i;
            #20;
            // $display("bcd in: %b, cathode out: %b", temp2[3:0], temp4[6:0]);
            $display("binary in: %b, cathode: %b, anode: %b", temp2, temp1[7:0], temp3[3:0]);
			// $display("integer: %3d binary: %b bcd: %b", i, temp2[13:0], temp1[15:0]);
        end
		$finish;
	end

    integer imove;
    // initial begin
    //     m0 = 0;
    //     #20
    //     $display("Loading mem %b", hi);
    //     // $readmemh({FILES_PATH, "Notes.mem"}, NOTES);
    //     $readmemh("Notes.mem", NOTES);
    //     #10
    //     for(i = 0; i < 16; i = i + 1) begin
    //         #20;
    //         maybe = $urandom%2;
	// 		m1 = maybe ? (-1 * i * 64) : (i * 64);
	// 		$display("maybe: %b m1: %b", maybe, m1);
    //         // $display("i: %d notes: %b", i, NOTES[i]);
    //         // $display("1st bit: %b", NOTES[i][3]);
    //         // if(NOTES[i][3] == 0) begin
    //         //     $display("zero %b", felix);
    //         // end else begin
    //         //     $display("not zero %b", felix);
    //         // end
    //     end
	// 	$finish;
	// end

    // reg[31:0] NOTE_POS1[0:39];
    // reg[31:0] NOTE_POS2[0:39];
    // reg NOTE_SPEED = 1;
    // always @(posedge clock) begin
	// 	for(imove = 0; imove < 40; imove = imove + 1) begin
	// 		NOTE_POS1[imove] = NOTE_POS1[imove] + NOTE_SPEED;
    //         NOTE_POS2[imove] = NOTE_POS2[imove] + NOTE_SPEED;
	// 	end
	// end

    // always @(posedge clock) begin
    //     $display("integer: %b", m0);
    //     for(i = 0; i < MAX_NOTES_ON_SCREEN; i = i + 1) begin
    //         m0[i] = ~m0[i];
    //     end
    //     $display("integer: %b", m0);
    // end

    always
        #5 clock = !clock;

endmodule

PS2Interface/gtkwave.vcd
$date
	Tue Nov 30 16:15:36 2021
$end
$version
	Icarus Verilog
$end
$timescale
	10ps
$end
$scope module custom_tb $end
$var wire 32 ! in0 [31:0] $end
$var wire 32 " in1 [31:0] $end
$var wire 32 # in2 [31:0] $end
$var wire 32 $ temp2 [31:0] $end
$var wire 32 % temp4 [31:0] $end
$var wire 32 & temp3 [31:0] $end
$var wire 32 ' temp1 [31:0] $end
$var wire 1 ( hi $end
$var wire 21 ) felix [20:0] $end
$var reg 1 * clock $end
$var integer 32 + i [31:0] $end
$var integer 32 , m0 [31:0] $end
$var integer 32 - m1 [31:0] $end
$var integer 32 . m2 [31:0] $end
$scope module fsklefj $end
$var wire 1 / bcd0 $end
$var wire 1 0 bcd1 $end
$var wire 1 1 bcd2 $end
$var wire 1 2 bcd3 $end
$var wire 1 3 bcd4 $end
$var wire 1 4 bcd5 $end
$var wire 1 5 bcd6 $end
$var wire 1 6 bcd7 $end
$var wire 1 7 bcd8 $end
$var wire 1 8 bcd9 $end
$var wire 4 9 val_in [3:0] $end
$var wire 7 : led_out [6:0] $end
$upscope $end
$scope module segtest $end
$var wire 4 ; an_out [3:0] $end
$var wire 1 * clk_in $end
$var wire 1 < rst_in $end
$var wire 32 = val_in [31:0] $end
$var wire 7 > led_out [6:0] $end
$var wire 8 ? cat_out [7:0] $end
$var wire 16 @ bcd [15:0] $end
$var reg 4 A routed_vals [3:0] $end
$var reg 32 B segment_counter [31:0] $end
$var reg 4 C segment_state [3:0] $end
$scope module bintobcd $end
$var wire 14 D bin [13:0] $end
$var reg 16 E bcd [15:0] $end
$var integer 32 F i [31:0] $end
$upscope $end
$scope module my_converter $end
$var wire 1 G bcd0 $end
$var wire 1 H bcd1 $end
$var wire 1 I bcd2 $end
$var wire 1 J bcd3 $end
$var wire 1 K bcd4 $end
$var wire 1 L bcd5 $end
$var wire 1 M bcd6 $end
$var wire 1 N bcd7 $end
$var wire 1 O bcd8 $end
$var wire 1 P bcd9 $end
$var wire 4 Q val_in [3:0] $end
$var wire 7 R led_out [6:0] $end
$upscope $end
$upscope $end
$upscope $end
$enddefinitions $end
#0
$dumpvars
bx R
bx Q
xP
xO
xN
xM
xL
xK
xJ
xI
xH
xG
b1110 F
b0 E
b0 D
b1 C
b0 B
bx A
b0 @
b1xxxxxxx ?
bx >
b0 =
0<
b1110 ;
b1 :
b0 9
08
07
06
05
04
03
02
01
00
1/
bx .
bx -
b0 ,
b0 +
0*
b0 )
0(
bz1xxxxxxx '
bz1110 &
bz0000001 %
b0 $
bx #
bx "
b0 !
$end
#50
b1 B
1*
#100
0*
#150
b10 B
1*
#200
0/
bz1001111 %
b1001111 :
10
b1 @
b1 E
b1110 F
1(
b1 )
b1 9
b1 D
0*
b1 $
b1 =
b1 !
b1 ,
b1 +
#250
1G
0K
0O
0I
bz10000001 '
b10000001 ?
b1 >
b1 R
0M
0H
0J
0L
0N
0P
b0 A
b0 Q
bz1101 &
b1101 ;
b10 C
b0 B
1*
#300
0*
#350
b1 B
1*
#400
0/
bz0010010 %
b10010 :
11
00
b1110 F
b10 @
b10 E
b10 )
b10 9
b10 D
0*
b10 $
b10 =
b10 !
b10 ,
b10 +
#450
b10 B
1*
#500
0*
#550
bz1011 &
b1011 ;
b100 C
b0 B
1*
#600
bz0000110 %
b110 :
01
12
b1110 F
b11 @
b11 E
b11 )
b11 9
b11 D
0*
b11 $
b11 =
b11 !
b11 ,
b11 +
#650
b1 B
1*
#700
0*
#750
b10 B
1*
#800
bz1001100 %
b1001100 :
0/
13
02
b1110 F
b100 @
b100 E
b100 )
b100 9
b100 D
0*
b100 $
b100 =
b100 !
b100 ,
b100 +
#850
bz0111 &
b111 ;
b1000 C
b0 B
1*
#900
0*
#950
b1 B
1*
#1000
03
bz0100010 %
b100010 :
14
b1110 F
b101 @
b101 E
b101 )
b101 9
b101 D
0*
b101 $
b101 =
b101 !
b101 ,
b101 +
#1050
b10 B
1*
#1100
0*
#1150
1L
0G
bz10100010 '
b10100010 ?
b100010 >
b100010 R
0H
b101 A
b101 Q
bz1110 &
b1110 ;
b1 C
b0 B
1*
#1200
bz0100000 %
b100000 :
03
15
04
b1110 F
b110 @
b110 E
b110 )
b110 9
b110 D
0*
b110 $
b110 =
b110 !
b110 ,
b110 +
#1250
b1 B
1*
#1300
0*
#1350
b10 B
1*
#1400
05
bz0001111 %
b1111 :
16
b1110 F
b111 @
b111 E
b111 )
b111 9
b111 D
0*
b111 $
b111 =
b111 !
b111 ,
b111 +
#1450
1G
0K
bz10000001 '
b10000001 ?
b1 >
b1 R
0L
b0 A
b0 Q
bz1101 &
b1101 ;
b10 C
b0 B
1*
#1500
0*
#1550
b1 B
1*
#1600
17
bz0000000 %
b0 :
06
b1110 F
b1000 @
b1000 E
b1000 )
b1000 9
b1000 D
0*
b1000 $
b1000 =
b1000 !
b1000 ,
b1000 +
#1650
b10 B
1*
#1700
0*
#1750
bz1011 &
b1011 ;
b100 C
b0 B
1*
#1800
07
bz0000100 %
b100 :
18
b1110 F
b1001 @
b1001 E
b1001 )
b1001 9
b1001 D
0*
b1001 $
b1001 =
b1001 !
b1001 ,
b1001 +
#1850
b1 B
1*
#1900
0*
#1950
b10 B
1*
#2000
07
bz0000000 %
b0 :
08
b1110 F
b10000 @
b10000 E
b1010 )
b1010 9
b1010 D
0*
b1010 $
b1010 =
b1010 !
b1010 ,
b1010 +
#2050
bz0111 &
b111 ;
b1000 C
b0 B
1*
#2100
0*
#2150
b1 B
1*
#2200
b1110 F
b10001 @
b10001 E
b1011 )
b1011 9
b1011 D
0*
b1011 $
b1011 =
b1011 !
b1011 ,
b1011 +
#2250
b10 B
1*
#2300
0*
#2350
0G
bz11001111 '
b11001111 ?
b1001111 >
b1001111 R
1H
b1 A
b1 Q
bz1110 &
b1110 ;
b1 C
b0 B
1*
#2400
07
b1110 F
b10010 @
b10010 E
b1100 )
b1100 9
b1100 D
0*
b1100 $
b1100 =
b1100 !
b1100 ,
b1100 +
#2450
b1 B
1*
#2500
0*
#2550
b10 B
1*
#2600
b1110 F
b10011 @
b10011 E
b1101 )
b1101 9
b1101 D
0*
b1101 $
b1101 =
b1101 !
b1101 ,
b1101 +
#2650
bz1101 &
b1101 ;
b10 C
b0 B
1*
#2700
0*
#2750
b1 B
1*
#2800
b1110 F
b10100 @
b10100 E
b1110 )
b1110 9
b1110 D
0*
b1110 $
b1110 =
b1110 !
b1110 ,
b1110 +
#2850
b10 B
1*
#2900
0*
#2950
1G
bz10000001 '
b10000001 ?
b1 >
b1 R
0H
b0 A
b0 Q
bz1011 &
b1011 ;
b100 C
b0 B
1*
#3000
b1110 F
b10101 @
b10101 E
b1111 )
b1111 9
b1111 D
0*
b1111 $
b1111 =
b1111 !
b1111 ,
b1111 +
#3050
b1 B
1*
#3100
0*
#3150
b10 B
1*
#3200
0*
b10000 +
